elexon_bmrs/__init__.py
elexon_bmrs/client.py
elexon_bmrs/enums.py
elexon_bmrs/exceptions.py
elexon_bmrs/field_mixins.py
elexon_bmrs/generated_client.py
elexon_bmrs/generated_models.py
elexon_bmrs/models.py
elexon_bmrs/py.typed
elexon_bmrs/response_types.py
elexon_bmrs/untyped_models.py
elexon_bmrs/validators.py
elexon_bmrs-0.3.0.dist-info/licenses/LICENSE
elexon_bmrs-0.3.0.dist-info/METADATA
elexon_bmrs-0.3.0.dist-info/WHEEL
elexon_bmrs-0.3.0.dist-info/top_level.txt
elexon_bmrs-0.3.0.dist-info/RECORD
