Metadata-Version: 2.4
Name: elexon-bmrs
Version: 0.3.0
Summary: Python client library for the Elexon BMRS (Balancing Mechanism Reporting Service) API
Author-email: Benjamin Watts <benjamin.watts@example.com>
Maintainer-email: Benjamin Watts <benjamin.watts@example.com>
Project-URL: Homepage, https://github.com/BenjaminWatts/balancing
Project-URL: Documentation, https://benjaminwatts.github.io/balancing/
Project-URL: Repository, https://github.com/BenjaminWatts/balancing
Project-URL: Issues, https://github.com/BenjaminWatts/balancing/issues
Keywords: elexon,bmrs,energy,electricity,uk,api,client,balancing-mechanism,power-market,energy-data
Classifier: Development Status :: 4 - Beta
Classifier: Intended Audience :: Developers
Classifier: Intended Audience :: Science/Research
Classifier: License :: OSI Approved :: MIT License
Classifier: Natural Language :: English
Classifier: Operating System :: OS Independent
Classifier: Programming Language :: Python :: 3
Classifier: Programming Language :: Python :: 3.8
Classifier: Programming Language :: Python :: 3.9
Classifier: Programming Language :: Python :: 3.10
Classifier: Programming Language :: Python :: 3.11
Classifier: Programming Language :: Python :: 3.12
Classifier: Topic :: Software Development :: Libraries :: Python Modules
Classifier: Topic :: Scientific/Engineering
Classifier: Typing :: Typed
Requires-Python: >=3.8
License-File: LICENSE
Requires-Dist: requests>=2.31.0
Requires-Dist: python-dateutil>=2.8.2
Requires-Dist: pydantic>=2.0.0
Provides-Extra: dev
Requires-Dist: pytest>=7.4.0; extra == "dev"
Requires-Dist: pytest-cov>=4.1.0; extra == "dev"
Requires-Dist: black>=23.7.0; extra == "dev"
Requires-Dist: flake8>=6.1.0; extra == "dev"
Requires-Dist: mypy>=1.5.0; extra == "dev"
Requires-Dist: isort>=5.12.0; extra == "dev"
Dynamic: license-file
